stream_pose_ml/LICENSE
stream_pose_ml/__init__.py
stream_pose_ml/ml_flow_client.py
stream_pose_ml/pytest.ini
stream_pose_ml/stream_pose_client.py
stream_pose_ml/blaze_pose/__init__.py
stream_pose_ml/blaze_pose/blaze_pose_frame.py
stream_pose_ml/blaze_pose/blaze_pose_sequence.py
stream_pose_ml/blaze_pose/enumerations.py
stream_pose_ml/blaze_pose/mediapipe_client.py
stream_pose_ml/blaze_pose/openpose_mediapipe_transformer.py
stream_pose_ml/geometry/__init__.py
stream_pose_ml/geometry/angle.py
stream_pose_ml/geometry/distance.py
stream_pose_ml/geometry/joint.py
stream_pose_ml/geometry/vector.py
stream_pose_ml/jobs/__init__.py
stream_pose_ml/jobs/build_and_format_dataset_job.py
stream_pose_ml/jobs/process_video_job.py
stream_pose_ml/jobs/process_videos_job.py
stream_pose_ml/learning/__init__.py
stream_pose_ml/learning/dataset.py
stream_pose_ml/learning/labeled_clip.py
stream_pose_ml/learning/labeled_frame.py
stream_pose_ml/learning/model_builder.py
stream_pose_ml/learning/sequence_transformer.py
stream_pose_ml/learning/temporal_feature_pooling.py
stream_pose_ml/learning/trained_model.py
stream_pose_ml/notebooks/example_usage.ipynb
stream_pose_ml/serializers/__init__.py
stream_pose_ml/serializers/angle_serializer.py
stream_pose_ml/serializers/blaze_pose_frame_serializer.py
stream_pose_ml/serializers/blaze_pose_sequence_serializer.py
stream_pose_ml/serializers/dataset_serializer.py
stream_pose_ml/serializers/distance_serializer.py
stream_pose_ml/serializers/joint_serializer.py
stream_pose_ml/serializers/labeled_clip_serializer.py
stream_pose_ml/serializers/labeled_frame_serializer.py
stream_pose_ml/serializers/vector_serializer.py
stream_pose_ml/services/__init__.py
stream_pose_ml/services/annotation_transformer_service.py
stream_pose_ml/services/segmentation_service.py
stream_pose_ml/services/video_data_merge_service.py
stream_pose_ml/services/video_data_service.py
stream_pose_ml/tests/__init__.py
stream_pose_ml/tests/conftest.py
stream_pose_ml-0.3.1.dist-info/METADATA
stream_pose_ml-0.3.1.dist-info/WHEEL
stream_pose_ml-0.3.1.dist-info/licenses/LICENSE
stream_pose_ml-0.3.1.dist-info/RECORD
