Metadata-Version: 2.4
Name: stream_pose_ml
Version: 0.3.1
Summary: A toolkit for realtime video classification tasks.
Project-URL: Homepage, https://github.com/mrilikecoding/StreamPoseML
Project-URL: Bug Tracker, https://github.com/mrilikecoding/StreamPoseML/issues
Author-email: Nate Green <nate@nate.green>
License: MIT License
License-File: LICENSE
Classifier: Development Status :: 3 - Alpha
Classifier: Intended Audience :: Developers
Classifier: Intended Audience :: Science/Research
Classifier: License :: OSI Approved :: MIT License
Classifier: Programming Language :: Python :: 3
Classifier: Programming Language :: Python :: 3.10
Classifier: Programming Language :: Python :: 3.11
Classifier: Topic :: Scientific/Engineering :: Artificial Intelligence
Classifier: Topic :: Software Development :: Libraries :: Python Modules
Requires-Python: <3.12,>=3.10
Requires-Dist: imbalanced-learn==0.10.1
Requires-Dist: kneed==0.8.5
Requires-Dist: matplotlib==3.7.0
Requires-Dist: mediapipe>=0.10.18
Requires-Dist: mlflow<2.21.0,>=2.18.0
Requires-Dist: numpy==1.24.2
Requires-Dist: opencv-contrib-python==4.8.1.78
Requires-Dist: pandas==1.5.3
Requires-Dist: pywavelets==1.4.1
Requires-Dist: pyyaml
Requires-Dist: scikit-learn==1.2.1
Requires-Dist: scipy==1.11.2
Requires-Dist: seaborn==0.12.2
Requires-Dist: tqdm==4.66.3
Requires-Dist: tslearn==0.6.2
Requires-Dist: xgboost==1.7.4
Provides-Extra: api
Requires-Dist: dnspython>=2.2.1; extra == 'api'
Requires-Dist: eventlet>=0.33.0; extra == 'api'
Requires-Dist: flask-cors>=3.0.10; extra == 'api'
Requires-Dist: flask-socketio>=5.3.3; extra == 'api'
Requires-Dist: flask>=2.2.2; extra == 'api'
Requires-Dist: python-engineio>=4.4.0; extra == 'api'
Requires-Dist: requests>=2.28.2; extra == 'api'
Requires-Dist: werkzeug>=2.2.2; extra == 'api'
Provides-Extra: dev
Requires-Dist: black>=23.7.0; extra == 'dev'
Requires-Dist: build; extra == 'dev'
Requires-Dist: mypy>=1.5.0; extra == 'dev'
Requires-Dist: pytest-cov>=4.1.0; extra == 'dev'
Requires-Dist: pytest-emoji; extra == 'dev'
Requires-Dist: pytest>=7.4.0; extra == 'dev'
Requires-Dist: ruff>=0.0.287; extra == 'dev'
Requires-Dist: twine; extra == 'dev'
